finmeter/__init__.py
finmeter/download.py
finmeter/finmeter.py
finmeter/hyphenate.py
finmeter/kalevala.py
finmeter/lwvlib.py
finmeter/meta4meaning_fi.py
finmeter/metaphor.py
finmeter/meters.json
finmeter/semantics.py
finmeter/sentiment/__init__.py
finmeter/sentiment/checkpoint
finmeter/sentiment/dan_eval.py
finmeter/sentiment/pickle2.py
finmeter/sentiment/predict_sentiment.py
finmeter/sentiment/senti_model.bin.data-00000-of-00001
finmeter/sentiment/senti_model.bin.index
finmeter/sentiment/senti_model.bin.meta
finmeter/sentiment/checkpoints/en-es-bimap-1.bin
finmeter/sentiment/utils/__init__.py
finmeter/sentiment/utils/bdi.py
finmeter/sentiment/utils/cupy_utils.py
finmeter/sentiment/utils/dataset.py
finmeter/sentiment/utils/math.py
finmeter/sentiment/utils/model.py
finmeter/utils/metaphor.py
finmeter-2.0.1.dist-info/METADATA
finmeter-2.0.1.dist-info/RECORD
finmeter-2.0.1.dist-info/WHEEL
finmeter-2.0.1.dist-info/top_level.txt
