Metadata-Version: 2.1
Name: finmeter
Version: 2.0.1
Summary: Hyphenator and poem analysis for Finnish
Home-page: https://github.com/mikahama/FinMeter
Author: Mika Hämäläinen, Dept. of  Digital Humanities, University of Helsinki
Author-email: mika.hamalainen@helsinki.fi
License: Apache License, Version 2.0
Keywords: Finnish poetry meter syllables hyphenation rhyme
Platform: UNKNOWN
Classifier: Development Status :: 5 - Production/Stable
Classifier: Intended Audience :: Developers
Classifier: Topic :: Text Processing
Classifier: Natural Language :: Finnish
Classifier: Programming Language :: Python :: 3
Requires-Dist: unidecode
Requires-Dist: sklearn
Requires-Dist: mikatools (>=0.0.7)
Requires-Dist: numpy
Requires-Dist: scipy
Requires-Dist: tqdm
Requires-Dist: hickle
Requires-Dist: argparse
Requires-Dist: uralicNLP
